mimejson-0.1.0.dist-info/METADATA
mimejson-0.1.0.dist-info/metadata.json
mimejson-0.1.0.dist-info/DESCRIPTION.rst
mimejson-0.1.0.dist-info/WHEEL
mimejson-0.1.0.dist-info/top_level.txt
mimejson-0.1.0.dist-info/RECORD
mimejson/__init__.py
mimejson/mimejson.py
mimejson/VERSION
mimejson/mimetype/__init__.py
mimejson/mimetype/video_opencv.py
mimejson/mimetype/file.py
mimejson/mimetype/png.py
mimejson/mimetype/jpg.py
