Metadata-Version: 2.0
Name: mimejson
Version: 0.1.0
Summary: Serialize and transport multipart semi-structured objects in a reflexive way close to standards.
Home-page: https://github.com/wideioltd/mimejson/
Author: WIDE IO LTD
Author-email: support@wide.io
License: BSD
Platform: UNKNOWN
Classifier: Development Status :: 3 - Alpha
Classifier: Intended Audience :: Developers
Classifier: Natural Language :: English
Classifier: License :: OSI Approved :: BSD License
Classifier: Programming Language :: Python
Classifier: Programming Language :: Python :: 2.7
Classifier: Programming Language :: Python :: Implementation :: CPython
Requires-Dist: requests
